[{"key":2,"pos":0},{"key":3,"pos":1000},{"key":4,"pos":2000},{"key":5,"pos":3000},{"key":6,"pos":4000},{"key":7,"pos":5000},{"key":8,"pos":6000},{"key":9,"pos":7000},{"key":10,"pos":8000},{"key":11,"pos":9000},{"key":12,"pos":10000},{"key":13,"pos":11000},{"key":14,"pos":12000},{"key":15,"pos":13000},{"key":16,"pos":14000},{"key":17,"pos":15000},{"key":18,"pos":16000},{"key":19,"pos":17000},{"key":20,"pos":18000},{"key":21,"pos":19000},{"key":22,"pos":20000},{"key":23,"pos":21000},{"key":24,"pos":22000},{"key":25,"pos":23000},{"key":26,"pos":24000},{"key":27,"pos":25000},{"key":28,"pos":26000},{"key":29,"pos":27000},{"key":30,"pos":28000},{"key":31,"pos":29000},{"key":32,"pos":30000},{"key":33,"pos":31000},{"key":34,"pos":32000},{"key":35,"pos":33000},{"key":36,"pos":34000},{"key":37,"pos":35000},{"key":38,"pos":36000},{"key":39,"pos":37000},{"key":40,"pos":38000},{"key":41,"pos":39000},{"key":42,"pos":40000},{"key":43,"pos":41000},{"key":44,"pos":42000},{"key":45,"pos":43000},{"key":46,"pos":44000},{"key":47,"pos":45000},{"key":48,"pos":46000},{"key":49,"pos":47000},{"key":50,"pos":48000},{"key":51,"pos":49000},{"key":52,"pos":50000},{"key":53,"pos":51000},{"key":54,"pos":52000},{"key":55,"pos":53000},{"key":56,"pos":54000},{"key":57,"pos":55000},{"key":58,"pos":56000},{"key":59,"pos":57000},{"key":60,"pos":58000},{"key":61,"pos":59000},{"key":62,"pos":60000},{"key":63,"pos":61000},{"key":64,"pos":62000},{"key":65,"pos":63000},{"key":66,"pos":64000},{"key":67,"pos":65000},{"key":68,"pos":66000},{"key":69,"pos":67000},{"key":70,"pos":68000},{"key":71,"pos":69000},{"key":72,"pos":70000},{"key":73,"pos":71000},{"key":74,"pos":72000},{"key":75,"pos":73000},{"key":76,"pos":74000},{"key":77,"pos":75000},{"key":78,"pos":76000},{"key":79,"pos":77000},{"key":80,"pos":78000},{"key":81,"pos":79000},{"key":82,"pos":80000},{"key":83,"pos":81000},{"key":84,"pos":82000},{"key":85,"pos":83000},{"key":86,"pos":84000},{"key":87,"pos":85000},{"key":88,"pos":86000},{"key":89,"pos":87000},{"key":90,"pos":88000},{"key":91,"pos":89000},{"key":92,"pos":90000},{"key":93,"pos":91000},{"key":94,"pos":92000},{"key":95,"pos":93000},{"key":96,"pos":94000},{"key":97,"pos":95000},{"key":98,"pos":96000},{"key":99,"pos":97000},{"key":100,"pos":98000},{"key":101,"pos":99000},{"key":102,"pos":100000},{"key":103,"pos":101000},{"key":104,"pos":102000},{"key":105,"pos":103000},{"key":106,"pos":104000},{"key":107,"pos":105000},{"key":108,"pos":106000},{"key":109,"pos":107000},{"key":110,"pos":108000},{"key":111,"pos":109000},{"key":112,"pos":110000},{"key":113,"pos":111000},{"key":114,"pos":112000},{"key":115,"pos":113000},{"key":116,"pos":114000},{"key":117,"pos":115000},{"key":118,"pos":116000},{"key":119,"pos":117000},{"key":120,"pos":118000},{"key":121,"pos":119000},{"key":122,"pos":120000},{"key":123,"pos":121000},{"key":124,"pos":122000},{"key":125,"pos":123000},{"key":126,"pos":124000},{"key":127,"pos":125000},{"key":128,"pos":126000},{"key":129,"pos":127000},{"key":130,"pos":128000},{"key":131,"pos":129000},{"key":132,"pos":130000},{"key":133,"pos":131000},{"key":134,"pos":132000}]